odoo/addons/product_form_sale_link/README.rst
odoo/addons/product_form_sale_link/__init__.py
odoo/addons/product_form_sale_link/__manifest__.py
odoo/addons/product_form_sale_link/i18n/ca.po
odoo/addons/product_form_sale_link/i18n/es.po
odoo/addons/product_form_sale_link/i18n/fr.po
odoo/addons/product_form_sale_link/i18n/it.po
odoo/addons/product_form_sale_link/i18n/nl.po
odoo/addons/product_form_sale_link/i18n/product_form_sale_link.pot
odoo/addons/product_form_sale_link/models/__init__.py
odoo/addons/product_form_sale_link/models/product_product.py
odoo/addons/product_form_sale_link/models/product_template.py
odoo/addons/product_form_sale_link/readme/CONTRIBUTORS.md
odoo/addons/product_form_sale_link/readme/DESCRIPTION.md
odoo/addons/product_form_sale_link/readme/USAGE.md
odoo/addons/product_form_sale_link/static/description/icon.png
odoo/addons/product_form_sale_link/static/description/index.html
odoo/addons/product_form_sale_link/static/description/product_sale.png
odoo/addons/product_form_sale_link/tests/__init__.py
odoo/addons/product_form_sale_link/tests/test_product.py
odoo/addons/product_form_sale_link/views/product_product.xml
odoo/addons/product_form_sale_link/views/product_template.xml
odoo/addons/product_form_sale_link/views/sale_order_line.xml
odoo_addon_product_form_sale_link-18.0.1.0.1.2.dist-info/METADATA
odoo_addon_product_form_sale_link-18.0.1.0.1.2.dist-info/WHEEL
odoo_addon_product_form_sale_link-18.0.1.0.1.2.dist-info/top_level.txt
odoo_addon_product_form_sale_link-18.0.1.0.1.2.dist-info/RECORD
