Metadata-Version: 2.1
Name: odoo-addon-product_form_sale_link
Version: 18.0.1.0.1.2
Requires-Python: >=3.10
Requires-Dist: odoo==18.0.*
Summary: Adds a button on product forms to access Sale Lines
Home-page: https://github.com/OCA/sale-workflow
License: AGPL-3
Author: ACSONE SA/NV,Odoo Community Association (OCA)
Author-email: support@odoo-community.org
Classifier: Programming Language :: Python
Classifier: Framework :: Odoo
Classifier: Framework :: Odoo :: 18.0
Classifier: License :: OSI Approved :: GNU Affero General Public License v3
